{"error": "none", "areas_string": "577772.0;793129.0;1608914.0;417693.0;598882.0;569060.0;528405.0;1075125.0;132106.0;10319.0;263175.0;22906.0;155690.0;32407.0;68279.0;999804.0;360445.0;119261.0;946042.0;94243.0;696164.0;81074.0;478252.0;790168.0;214780.0", "color_data": {"id_1": "#e7298a", "id_2": "#66a61e", "id_3": "#d95f02", "id_4": "#7570b3", "id_5": "#e7298a", "id_6": "#1b9e77", "id_7": "#1b9e77", "id_8": "#66a61e", "id_9": "#d95f02", "id_10": "#d95f02", "id_11": "#7570b3", "id_12": "#1b9e77", "id_13": "#7570b3", "id_14": "#1b9e77", "id_15": "#66a61e", "id_16": "#e6ab02", "id_17": "#e6ab02", "id_18": "#e7298a", "id_19": "#e6ab02", "id_20": "#e7298a", "id_21": "#7570b3", "id_22": "#d95f02", "id_23": "#66a61e", "id_24": "#e6ab02", "id_25": "#1b9e77"}, "tooltip": {"label": "Population (1998)", "unit": "People", "data": {"id_1": {"name": "Banteay Meanchey", "value": 577772.0}, "id_2": {"name": "Battambang", "value": 793129.0}, "id_3": {"name": "Kampong Cham", "value": 1608914.0}, "id_4": {"name": "Kampong Chhnang", "value": 417693.0}, "id_5": {"name": "Kampong Speu", "value": 598882.0}, "id_6": {"name": "Kampong Thom", "value": 569060.0}, "id_7": {"name": "Kampot", "value": 528405.0}, "id_8": {"name": "Kandal", "value": 1075125.0}, "id_9": {"name": "Koh Kong", "value": 132106.0}, "id_10": {"name": "Kep", "value": 10319.0}, "id_11": {"name": "Kratie", "value": 263175.0}, "id_12": {"name": "Pailin", "value": 22906.0}, "id_13": {"name": "Preah Sihanouk", "value": 155690.0}, "id_14": {"name": "Mondul Kiri", "value": 32407.0}, "id_15": {"name": "Otdar Meanchey", "value": 68279.0}, "id_16": {"name": "Phnom Penh", "value": 999804.0}, "id_17": {"name": "Pursat", "value": 360445.0}, "id_18": {"name": "Preah Vihear", "value": 119261.0}, "id_19": {"name": "Prey Veng", "value": 946042.0}, "id_20": {"name": "Ratanak Kiri", "value": 94243.0}, "id_21": {"name": "Siem Reap", "value": 696164.0}, "id_22": {"name": "Stung Treng", "value": 81074.0}, "id_23": {"name": "Svay Rieng", "value": 478252.0}, "id_24": {"name": "Takeo", "value": 790168.0}, "id_25": {"name": "Tbong Khmum", "value": 214780.0}}}, "grid_document": {"name": "Cambodia", "width": 4, "height": 26, "edit_mask": [{"row": null, "col": 0, "editable": false}, {"row": null, "col": 1, "editable": false}, {"row": 0, "col": null, "editable": false}, {"row": null, "col": 3, "type": "color"}, {"row": null, "col": 2, "type": "number", "min": 0, "max": null}, {"row": 0, "col": null, "type": "text"}, {"row": 0, "col": 2, "editable": true}], "contents": ["Province", "Population", "Population (1998) (People)", "Colour", "Banteay Meanchey", "859545", "577772", "#e7298a", "Battambang", "987400", "793129", "#66a61e", "Kampong Cham", "895763", "1608914", "#d95f02", "Kampong Chhnang", "525932", "417693", "#7570b3", "Kampong Speu", "872219", "598882", "#e7298a", "Kampong Thom", "677260", "569060", "#1b9e77", "Kampot", "592845", "528405", "#1b9e77", "Kandal", "1195547", "1075125", "#66a61e", "Koh Kong", "123618", "132106", "#d95f02", "Kep", "41798", "10319", "#d95f02", "Kratie", "372825", "263175", "#7570b3", "Pailin", "71600", "22906", "#1b9e77", "Preah Sihanouk", "302887", "155690", "#7570b3", "Mondul Kiri", "88649", "32407", "#1b9e77", "Otdar Meanchey", "261252", "68279", "#66a61e", "Phnom Penh", "2129371", "999804", "#e6ab02", "Pursat", "411759", "360445", "#e6ab02", "Preah Vihear", "251352", "119261", "#e7298a", "Prey Veng", "1057428", "946042", "#e6ab02", "Ratanak Kiri", "204027", "94243", "#e7298a", "Siem Reap", "1006512", "696164", "#7570b3", "Stung Treng", "159565", "81074", "#d95f02", "Svay Rieng", "524554", "478252", "#66a61e", "Takeo", "899485", "790168", "#e6ab02", "Tbong Khmum", "775296", "214780", "#1b9e77"]}, "unique_sharing_key": "dsytm4w2nyrr9xjg770zi5mikbiy68gq"}
